__init__.py
crawler.py
fastcrawler-0.0.1.dist-info/LICENSE
fastcrawler-0.0.1.dist-info/METADATA
fastcrawler-0.0.1.dist-info/WHEEL
fastcrawler-0.0.1.dist-info/top_level.txt
fastcrawler-0.0.1.dist-info/RECORD
